{"objectList":[{"id":74250,"obid":73735429,"ok2id":3,"geox":231951,"geoy":2509601,"bgid":17,"strasse":"Dora-Benjamin-Park","hausnr":"8-10","plz":"10245","ort":"Berlin","wohnflaeche":68,"zimmeranzahl":2,"baujahr":null,"courtage":"4,17 % brutto","kaufpreis":300000,"kaufvermietet":false,"nebenkosten":null,"zusatzkosten":null,"ueberschrift":"Pure Lebensfreude! Schicke Dachgeschosswohnung mit Balkon nahe Boxhagener Platz und Simon-Dach-Kiez","url":null,"edatum":1394492400000,"parkflaechenzahl":1,"parkflaechenpreis":null,"etage":null,"mieteinnahmenpromonat":null,"heizkosten":null,"letzte_modernisierung":null,"keller":false,"barrierefrei":false,"denkmalobjekt":false,"isSkyline":true,"dominatedBy":null},{"id":93241,"obid":48219677,"ok2id":118,"geox":null,"geoy":null,"bgid":17,"strasse":null,"hausnr":"ANONYM","plz":"10405","ort":"Berlin","wohnflaeche":134,"zimmeranzahl":4,"baujahr":null,"courtage":null,"kaufpreis":374000,"kaufvermietet":null,"nebenkosten":null,"zusatzkosten":null,"ueberschrift":"Altbauflair neu gebaut - Krügers Gartenhaus !  www.kruegers-gartenhaus.de","url":null,"edatum":1226876400000,"parkflaechenzahl":1,"parkflaechenpreis":null,"etage":null,"mieteinnahmenpromonat":null,"heizkosten":null,"letzte_modernisierung":null,"keller":false,"barrierefrei":false,"denkmalobjekt":null,"isSkyline":true,"dominatedBy":null},{"id":71844,"obid":73226318,"ok2id":118,"geox":230433,"geoy":2512385,"bgid":17,"strasse":"Richard-Sorge Str.","hausnr":"68","plz":"10249","ort":"Friedrichshain","wohnflaeche":82,"zimmeranzahl":2,"baujahr":null,"courtage":"7,14% von Verkaufspreis inkl. 19% MwSt.","kaufpreis":367970,"kaufvermietet":false,"nebenkosten":null,"zusatzkosten":null,"ueberschrift":"+++ WIR STARTEN ++ KIEZLAGE MIT INDIVIDUELLEN WÜNSCHEN MÖGLICH++ GEHOBENE AUSSTATTUNG +++","url":null,"edatum":1391727600000,"parkflaechenzahl":null,"parkflaechenpreis":null,"etage":"5","mieteinnahmenpromonat":null,"heizkosten":null,"letzte_modernisierung":null,"keller":false,"barrierefrei":false,"denkmalobjekt":false,"isSkyline":true,"dominatedBy":null},{"id":13804,"obid":42046483,"ok2id":0,"geox":232202,"geoy":2511898,"bgid":17,"strasse":"Schreinerstraße","hausnr":"ANONYM","plz":"10247","ort":"Berlin","wohnflaeche":110,"zimmeranzahl":4,"baujahr":2006,"courtage":"3,57 % inkl. MwSt","kaufpreis":172000,"kaufvermietet":null,"nebenkosten":null,"zusatzkosten":null,"ueberschrift":"ANONYM","url":null,"edatum":1182463200000,"parkflaechenzahl":null,"parkflaechenpreis":null,"etage":null,"mieteinnahmenpromonat":null,"heizkosten":null,"letzte_modernisierung":null,"keller":null,"barrierefrei":null,"denkmalobjekt":null,"isSkyline":true,"dominatedBy":null},{"id":44768,"obid":63276183,"ok2id":118,"geox":231421,"geoy":2510989,"bgid":17,"strasse":"Gärtnerstrasse","hausnr":"2","plz":"10245","ort":"Berlin","wohnflaeche":81,"zimmeranzahl":3,"baujahr":null,"courtage":"7,14% des Kaufpreises inkl. MwSt.","kaufpreis":150000,"kaufvermietet":null,"nebenkosten":null,"zusatzkosten":null,"ueberschrift":"Vermietete 3 Zimmer Wohnung nahe Boxhagener Platz","url":null,"edatum":1324594800000,"parkflaechenzahl":null,"parkflaechenpreis":null,"etage":"2","mieteinnahmenpromonat":null,"heizkosten":null,"letzte_modernisierung":null,"keller":false,"barrierefrei":null,"denkmalobjekt":null,"isSkyline":true,"dominatedBy":null}]}
